lonedev/__init__.py
lonedev/globalargs/__init__.py
lonedev/globalargs/global_args.py
lonedev/logger/__init__.py
lonedev/logger/__main__.py
lonedev/logger/logger.py
lonedev-0.0.6.dist-info/licenses/LICENSE
lonedev-0.0.6.dist-info/METADATA
lonedev-0.0.6.dist-info/WHEEL
lonedev-0.0.6.dist-info/top_level.txt
lonedev-0.0.6.dist-info/RECORD
