Metadata-Version: 2.4
Name: lonedev
Version: 0.0.6
Summary: A collection of utilities for Python development
Author-email: Bouhier Loan <loan.bouhier@gmail.com>
License: MIT License
Project-URL: Homepage, https://github.com/bouhier-loan/lonedev.pyutils
Classifier: Programming Language :: Python :: 3
Classifier: Topic :: Software Development :: Libraries :: Python Modules
Requires-Python: >=3.12
License-File: LICENSE
Requires-Dist: rich>=13.9.4
Dynamic: license-file
